virgil_crypto/__init__.py
virgil_crypto/access_token_signer.py
virgil_crypto/card_crypto.py
virgil_crypto/crypto.py
virgil_crypto/errors/__init__.py
virgil_crypto/errors/virgil_crypto_error.py
virgil_crypto/hashes/__init__.py
virgil_crypto/hashes/hash_algorithm.py
virgil_crypto/keys/__init__.py
virgil_crypto/keys/key_pair_type.py
virgil_crypto/keys/virgil_key_pair.py
virgil_crypto/keys/virgil_private_key.py
virgil_crypto/keys/virgil_public_key.py
virgil_crypto/tests/__init__.py
virgil_crypto/tests/__init__.pyc
virgil_crypto/tests/access_token_signer_test.py
virgil_crypto/tests/access_token_signer_test.pyc
virgil_crypto/tests/card_crypto_test.py
virgil_crypto/tests/card_crypto_test.pyc
virgil_crypto/tests/cipher_test.py
virgil_crypto/tests/cipher_test.pyc
virgil_crypto/tests/compatibility_test.py
virgil_crypto/tests/compatibility_test.pyc
virgil_crypto/tests/crypto_formats_test.py
virgil_crypto/tests/crypto_test.py
virgil_crypto/tests/crypto_test.pyc
virgil_crypto/tests/signer_test.py
virgil_crypto/tests/signer_test.pyc
virgil_crypto/tests/stream_signer_test.py
virgil_crypto/tests/stream_signer_test.pyc
virgil_crypto/tests/data/sdk_compatibility_data.json
virgil_crypto-5.0.1.dist-info/DESCRIPTION.rst
virgil_crypto-5.0.1.dist-info/METADATA
virgil_crypto-5.0.1.dist-info/RECORD
virgil_crypto-5.0.1.dist-info/WHEEL
virgil_crypto-5.0.1.dist-info/metadata.json
virgil_crypto-5.0.1.dist-info/top_level.txt
